kryten/__init__.py
kryten/client.py
kryten/config.py
kryten/exceptions.py
kryten/health.py
kryten/kv_store.py
kryten/lifecycle_events.py
kryten/metrics_server.py
kryten/mock.py
kryten/models.py
kryten/subject_builder.py
kryten_py-0.11.6.dist-info/METADATA
kryten_py-0.11.6.dist-info/WHEEL
kryten_py-0.11.6.dist-info/licenses/LICENSE
kryten_py-0.11.6.dist-info/RECORD
