Metadata-Version: 2.4
Name: kryten-py
Version: 0.11.6
Summary: Python library for building CyTube microservices via Kryten bridge and NATS
Author: Development Team
License: MIT
License-File: LICENSE
Keywords: bot,cytube,microservices,nats,streaming
Classifier: Development Status :: 3 - Alpha
Classifier: Intended Audience :: Developers
Classifier: License :: OSI Approved :: MIT License
Classifier: Programming Language :: Python :: 3.10
Classifier: Programming Language :: Python :: 3.11
Classifier: Programming Language :: Python :: 3.12
Classifier: Topic :: Communications :: Chat
Classifier: Topic :: Software Development :: Libraries :: Python Modules
Requires-Python: >=3.10
Requires-Dist: aiohttp<4.0.0,>=3.9.0
Requires-Dist: nats-py<3.0.0,>=2.9.0
Requires-Dist: pydantic-settings<3.0.0,>=2.0.0
Requires-Dist: pydantic<3.0.0,>=2.0.0
Provides-Extra: all
Requires-Dist: python-dotenv<2.0.0,>=1.0.0; extra == 'all'
Requires-Dist: pyyaml<7.0.0,>=6.0; extra == 'all'
Provides-Extra: dotenv
Requires-Dist: python-dotenv<2.0.0,>=1.0.0; extra == 'dotenv'
Provides-Extra: yaml
Requires-Dist: pyyaml<7.0.0,>=6.0; extra == 'yaml'
